krausening/__init__.py
krausening/logging/__init__.py
krausening/logging/log_manager.py
krausening/properties/__init__.py
krausening/properties/property_encryptor.py
krausening/properties/property_manager.py
krausening-21.dist-info/METADATA
krausening-21.dist-info/WHEEL
krausening-21.dist-info/RECORD
