Metadata-Version: 2.3
Name: krausening
Version: 21
Summary: Python implementation of Krausening
License: MIT
Keywords: properties,configuration-management
Author: Eric Konieczny
Author-email: ekoniec1@gmail.com
Requires-Python: >=3.8
Classifier: License :: OSI Approved :: MIT License
Classifier: Programming Language :: Python :: 3
Classifier: Programming Language :: Python :: 3.8
Classifier: Programming Language :: Python :: 3.9
Classifier: Programming Language :: Python :: 3.10
Classifier: Programming Language :: Python :: 3.11
Classifier: Programming Language :: Python :: 3.12
Classifier: Programming Language :: Python :: 3.13
Requires-Dist: cryptography (>=42.0.0)
Requires-Dist: javaproperties (>=0.8.1) ; python_version >= "3.8" and python_version < "4.0"
Requires-Dist: watchdog (>=2.1.9)
Project-URL: Repository, https://github.com/TechnologyBrewery/krausening
